webkitapipy/__init__.py
webkitapipy/__main__.py
webkitapipy/allow.py
webkitapipy/allow2.py
webkitapipy/allow_unittest.py
webkitapipy/macho.py
webkitapipy/mypy_unittest.py
webkitapipy/program.py
webkitapipy/program_unittest.py
webkitapipy/reporter.py
webkitapipy/sdkdb.py
webkitapipy/sdkdb_unittest.py
webkitapipy/tbd.py
webkitapipy-0.1.0.dist-info/METADATA
webkitapipy-0.1.0.dist-info/WHEEL
webkitapipy-0.1.0.dist-info/entry_points.txt
webkitapipy-0.1.0.dist-info/top_level.txt
webkitapipy-0.1.0.dist-info/RECORD
